trytond/modules/health_services_lab/COPYING
trytond/modules/health_services_lab/README.rst
trytond/modules/health_services_lab/__init__.py
trytond/modules/health_services_lab/data/messages/messages.xml
trytond/modules/health_services_lab/exceptions.py
trytond/modules/health_services_lab/health_services_lab.py
trytond/modules/health_services_lab/health_services_lab_view.xml
trytond/modules/health_services_lab/locale/ar.po
trytond/modules/health_services_lab/locale/de.po
trytond/modules/health_services_lab/locale/el.po
trytond/modules/health_services_lab/locale/eo.po
trytond/modules/health_services_lab/locale/es.po
trytond/modules/health_services_lab/locale/fr.po
trytond/modules/health_services_lab/locale/health_services_lab.pot
trytond/modules/health_services_lab/locale/it_IT.po
trytond/modules/health_services_lab/locale/ja_JP.po
trytond/modules/health_services_lab/locale/ka.po
trytond/modules/health_services_lab/locale/lo.po
trytond/modules/health_services_lab/locale/pt_BR.po
trytond/modules/health_services_lab/locale/sv.po
trytond/modules/health_services_lab/locale/tr.po
trytond/modules/health_services_lab/locale/uk.po
trytond/modules/health_services_lab/locale/zh_CN.po
trytond/modules/health_services_lab/pyproject.toml
trytond/modules/health_services_lab/security/access_rights.xml
trytond/modules/health_services_lab/tests/__init__.py
trytond/modules/health_services_lab/tests/test_health_services_lab.py
trytond/modules/health_services_lab/tryton.cfg
trytond/modules/health_services_lab/view/gnuhealth_lab_request.xml
trytond/modules/health_services_lab/view/gnuhealth_lab_start_request.xml
trytond/modules/health_services_lab/wizard/__init__.py
trytond/modules/health_services_lab/wizard/create_health_service_invoice.xml
trytond/modules/health_services_lab/wizard/wizard_health_services.py
gnuhealth_services_lab-5.0.2.dist-info/METADATA
gnuhealth_services_lab-5.0.2.dist-info/WHEEL
gnuhealth_services_lab-5.0.2.dist-info/licenses/COPYING
gnuhealth_services_lab-5.0.2.dist-info/RECORD
